<?xml version="1.0" encoding="utf-8"?>
<shop>
    <spaceship>
        <array-life>
            <life mapName="Default" fee="0" image="0" level="0" value="800" />
            <life mapName="Primary" fee="500" image="0" level="1" value="1000" />
            <life mapName="Secondary" fee="1000" image="0" level="2" value="1200" />
            <life mapName="Advanced" fee="1500" image="0" level="3" value="1400" />
            <life mapName="Ultimate" fee="2000" image="0" level="4" value="1600" />
        </array-life>

        <array-defense>
            <defense mapName="Default" fee="0" image="0" level="0" value="100" />
            <defense mapName="Primary" fee="500" image="0" level="1" value="110" />
            <defense mapName="Secondary" fee="1000" image="0" level="2" value="120" />
            <defense mapName="Advanced" fee="1500" image="0" level="3" value="130" />
            <defense mapName="Ultimate" fee="2000" image="0" level="4" value="140" />
        </array-defense>

        <array-agility>
            <agility mapName="Default" fee="0" image="0" level="0" value="100" />
            <agility mapName="Primary" fee="500" image="0" level="1" value="110" />
            <agility mapName="Secondary" fee="1000" image="0" level="2" value="120" />
            <agility mapName="Advanced" fee="1500" image="0" level="3" value="130" />
            <agility mapName="Ultimate" fee="2000" image="0" level="4" value="140" />
        </array-agility>

        <array-shield>
            <shield mapName="Default" fee="0" image="0" level="0" value="60" />
            <shield mapName="Primary" fee="500" image="0" level="1" value="55" />
            <shield mapName="Secondary" fee="1000" image="0" level="2" value="50" />
            <shield mapName="Advanced" fee="1500" image="0" level="3" value="45" />
            <shield mapName="Ultimate" fee="2000" image="0" level="4" value="40" />
        </array-shield>
    </spaceship>

    <weapon>
        <array-power>
            <power mapName="Default" fee="0" image="0" level="0" value="100" />
            <power mapName="Primary" fee="500" image="0" level="1" value="120" />
            <power mapName="Secondary" fee="1000" image="0" level="2" value="140" />
            <power mapName="Advanced" fee="1500" image="0" level="3" value="160" />
            <power mapName="Ultimate" fee="2000" image="0" level="4" value="180" />
        </array-power>

        <array-speed>
            <speed mapName="Default" fee="0" image="0" level="0" value="100" />
            <speed mapName="Primary" fee="500" image="0" level="1" value="110" />
            <speed mapName="Secondary" fee="1000" image="0" level="2" value="120" />
            <speed mapName="Advanced" fee="1500" image="0" level="3" value="130" />
            <speed mapName="Ultimate" fee="2000" image="0" level="4" value="140" />
        </array-speed>

        <array-range>
            <range mapName="Default" fee="0" image="0" level="0" value="100" />
            <range mapName="Primary" fee="500" image="0" level="1" value="120" />
            <range mapName="Secondary" fee="1000" image="0" level="2" value="140" />
            <range mapName="Advanced" fee="1500" image="0" level="3" value="160" />
            <range mapName="Ultimate" fee="2000" image="0" level="4" value="180" />
        </array-range>

        <array-laser>
            <laser mapName="Default" fee="0" image="0" level="0" value="60" />
            <laser mapName="Primary" fee="500" image="0" level="1" value="55" />
            <laser mapName="Secondary" fee="1000" image="0" level="2" value="50" />
            <laser mapName="Advanced" fee="1500" image="0" level="3" value="45" />
            <laser mapName="Ultimate" fee="2000" image="0" level="4" value="40" />
        </array-laser>
    </weapon>
</shop>